LICENSE
nbt_structure_utils/__init__.py
nbt_structure_utils/block_state_transformations.py
nbt_structure_utils/blocks.py
nbt_structure_utils/entities.py
nbt_structure_utils/items.py
nbt_structure_utils/nbt_structure.py
nbt_structure_utils/shapes.py
nbt_structure_utils-0.3.0.dist-info/LICENSE
nbt_structure_utils-0.3.0.dist-info/METADATA
nbt_structure_utils-0.3.0.dist-info/WHEEL
nbt_structure_utils-0.3.0.dist-info/RECORD
