Metadata-Version: 2.1
Name: nbt-structure-utils
Version: 0.3.0
Summary: Create, read, and edit Minecraft NBT structure files.
Home-page: https://github.com/BenBenBenB/nbt-structure-utils
License: MIT
Keywords: minecraft,nbt-structure,nbt
Author: Ben Burton
Author-email: benjaminburtondev@gmail.com
Requires-Python: >=3.8,<4.0
Classifier: Development Status :: 3 - Alpha
Classifier: Intended Audience :: Developers
Classifier: License :: OSI Approved :: MIT License
Classifier: Operating System :: OS Independent
Classifier: Programming Language :: Python
Classifier: Programming Language :: Python :: 3
Classifier: Programming Language :: Python :: 3.8
Classifier: Programming Language :: Python :: 3.9
Classifier: Programming Language :: Python :: 3.10
Classifier: Programming Language :: Python :: 3.11
Classifier: Programming Language :: Python :: 3.10
Classifier: Programming Language :: Python :: 3.8
Classifier: Programming Language :: Python :: 3.9
Classifier: Topic :: Games/Entertainment
Classifier: Topic :: Software Development :: Libraries :: Python Modules
Requires-Dist: nbt (>=1.5.1,<2.0.0)
Requires-Dist: numpy (>=1.24.3,<2.0.0)
Project-URL: Repository, https://github.com/BenBenBenB/nbt-structure-utils
